{
  "components": {
    "nav": {
      "style": {
        "backgroundColor": "rgb(16, 17, 18)",
        "color": "rgb(240, 241, 242)",
        "fontFamily": "\"Roboto Condensed\", sans-serif",
        "fontSize": "16px",
        "height": "54px",
        "width": "1368px",
        "padding": "0px 16px",
        "margin": "0px",
        "border": {
          "color": "rgb(240, 241, 242)",
          "width": "0px",
          "radius": "0px"
        },
        "display": "flex",
        "position": "static"
      }
    },
    "regexInput": {
      "style": {
        "backgroundColor": "rgba(240, 241, 242, 0.05)",
        "color": "rgb(240, 241, 242)",
        "fontFamily": "\"Roboto Condensed\", sans-serif",
        "fontSize": "16px",
        "height": "16px",
        "width": "1000px",
        "padding": "0px",
        "margin": "0px",
        "border": {
          "color": "rgba(240, 241, 242, 0.05)",
          "width": "0px 0px 1px",
          "radius": "0px"
        },
        "display": "block",
        "position": "absolute"
      }
    },
    "flags": {
      "style": {
        "backgroundColor": "rgba(240, 241, 242, 0.35)",
        "color": "rgb(38, 41, 43)",
        "fontFamily": "\"Roboto Condensed\", sans-serif",
        "fontSize": "14px",
        "height": "16.2969px",
        "width": "60.8906px",
        "padding": "6px 12px",
        "margin": "0px 0px 0px 4px",
        "border": {
          "color": "rgb(38, 41, 43)",
          "width": "0px",
          "radius": "2px"
        },
        "display": "block",
        "position": "static"
      }
    },
    "editor": {
      "style": null
    },
    "rightPanel": {
      "style": null
    },
    "tabs": {
      "style": null
    }
  },
  "cssFiles": [
    {
      "href": "https://fonts.googleapis.com/css2?family=Roboto+Condensed:wght@400;700&family=Source+Code+Pro:wght@200;400;700&display=swap",
      "error": "Failed to read the 'cssRules' property from 'CSSStyleSheet': Cannot access rules"
    },
    {
      "href": "https://regexr.com/deploy/0e8dbde09.css",
      "rules": ".CodeMirror { font-family: monospace; height: 300px; color: rgb(0, 0, 0); }\n.CodeMirror-lines { padding: 4px 0px; }\n.CodeMirror pre { padding: 0px 4px; }\n.CodeMirror-gutter-filler, .CodeMirror-scrollbar-filler { background-color: rgb(255, 255, 255); }\n.CodeMirror-gutters { border-right: 1px solid rgb(221, 221, 221); background-color: rgb(247, 247, 247); white-space: nowrap; }\n.CodeMirror-linenumber { padding: 0px 3px 0px 5px; min-width: 20px; text-align: right; color: rgb(153, 153, 153); white-space: nowrap; }\n.CodeMirror-guttermarker { color: rgb(0, 0, 0); }\n.CodeMirror-guttermarker-subtle { color: rgb(153, 153, 153); }\n.CodeMirror-cursor { border-left: 1px solid rgb(0, 0, 0); border-right-width: medium; border-right-style: none; border-right-color: currentcolor; width: 0px; }\n.CodeMirror div.CodeMirror-secondarycursor { border-left: 1px solid silver; }\n.cm-fat-cursor .CodeMirror-cursor { width: auto; background: rgb(119, 238, 119); border: 0px !important; }\n.cm-fat-cursor div.CodeMirror-cursors { z-index: 1; }\n.cm-animate-fat-cursor { width: auto; border: 0px; animation: 1.06s steps(1) 0s infinite normal none running blink; background-color: rgb(119, 238, 119); }\n@-webkit-keyframes blink { \n  50% { background-color: transparent; }\n}\n@keyframes blink { \n  50% { background-color: transparent; }\n}\n.cm-tab { display: inline-block; text-decoration: inherit; }\n.CodeMirror-rulers { position: absolute; inset: -50px 0px -20px; overflow: hidden; }\n.CodeMirror-ruler { border-left: 1px solid rgb(204, 204, 204); top: 0px; bottom: 0px; position: absolute; }\n.cm-s-default .cm-header { color: rgb(0, 0, 255); }\n.cm-s-default .cm-quote { color: rgb(0, 153, 0); }\n.cm-negative { color: rgb(221, 68, 68); }\n.cm-positive { color: rgb(34, 153, 34); }\n.cm-header, .cm-strong { font-weight: 700; }\n.cm-em { font-style: italic; }\n.cm-link { text-decoration: underline; }\n.cm-strikethrough { text-decoration: line-through; }\n.cm-s-default .cm-keyword { color: rgb(119, 0, 136); }\n.cm-s-default .cm-atom { color: rgb(34, 17, 153); }\n.cm-s-default .cm-number { color: rgb(17, 102, 68); }\n.cm-s-default .cm-def { color: rgb(0, 0, 255); }\n.cm-s-default .cm-variable-2 { color: rgb(0, 85, 170); }\n.cm-s-default .cm-type, .cm-s-default .cm-variable-3 { color: rgb(0, 136, 85); }\n.cm-s-default .cm-comment { color: rgb(170, 85, 0); }\n.cm-s-default .cm-string { color: rgb(170, 17, 17); }\n.cm-s-default .cm-string-2 { color: rgb(255, 85, 0); }\n.cm-s-default .cm-meta { color: rgb(85, 85, 85); }\n.cm-s-default .cm-qualifier { color: rgb(85, 85, 85); }\n.cm-s-default .cm-builtin { color: rgb(51, 0, 170); }\n.cm-s-default .cm-bracket { color: rgb(153, 153, 119); }\n.cm-s-default .cm-tag { color: rgb(17, 119, 0); }\n.cm-s-default .cm-attribute { color: rgb(0, 0, 204); }\n.cm-s-default .cm-hr { color: rgb(153, 153, 153); }\n.cm-s-default .cm-link { color: rgb(0, 0, 204); }\n.cm-s-default .cm-error { color: red; }\n.cm-invalidchar { color: red; }\n.CodeMirror-composing { border-bottom: 2px solid; }\ndiv.CodeMir"
    }
  ],
  "colors": [
    "rgba(0, 0, 0, 0)",
    "rgb(240, 241, 242)",
    "rgb(16, 17, 18)",
    "rgb(112, 176, 224)",
    "rgb(89, 95, 100)",
    "rgb(0, 0, 0)",
    "rgb(40, 43, 45)",
    "rgb(126, 135, 142)",
    "rgb(183, 188, 192)",
    "rgb(183, 188, 192) rgb(58, 62, 65) rgb(183, 188, 192) rgb(183, 188, 192)",
    "rgb(183, 188, 192) rgb(183, 188, 192) rgba(240, 241, 242, 0.06)",
    "rgb(240, 241, 242) rgb(240, 241, 242) rgba(240, 241, 242, 0.05)",
    "rgb(58, 62, 65)",
    "rgb(183, 188, 192) rgb(183, 188, 192) rgb(58, 62, 65)",
    "rgb(40, 43, 45) rgb(183, 188, 192) rgb(183, 188, 192)",
    "rgb(215, 218, 220)",
    "rgb(128, 128, 128)",
    "rgba(126, 135, 142, 0.25) rgb(128, 128, 128) rgb(128, 128, 128)",
    "rgb(88, 94, 99)",
    "rgb(38, 41, 43)",
    "rgba(240, 241, 242, 0.35)",
    "rgb(221, 34, 34)",
    "rgba(240, 241, 242, 0.05)",
    "rgb(255, 255, 255)",
    "rgb(0, 0, 0) rgba(0, 0, 0, 0) rgb(0, 0, 0) rgb(0, 0, 0)",
    "rgb(0, 0, 0) rgb(0, 0, 0) rgb(0, 0, 0) rgb(16, 17, 18)",
    "rgba(0, 238, 0, 0.11)",
    "rgb(0, 170, 0)",
    "rgba(255, 238, 0, 0.3)",
    "rgb(221, 119, 0)",
    "rgb(85, 136, 255)",
    "rgb(0, 0, 0) rgb(0, 0, 0) rgba(0, 0, 0, 0)",
    "rgb(247, 247, 247)",
    "rgb(0, 0, 0) rgb(221, 221, 221) rgb(0, 0, 0) rgb(0, 0, 0)",
    "rgba(240, 241, 242, 0.75)",
    "rgba(240, 241, 242, 0.2)",
    "rgb(16, 17, 18) rgba(0, 0, 0, 0) rgb(16, 17, 18) rgb(16, 17, 18)",
    "rgb(16, 17, 18) rgb(16, 17, 18) rgba(0, 0, 0, 0)",
    "rgb(16, 17, 18) rgb(221, 221, 221) rgb(16, 17, 18) rgb(16, 17, 18)",
    "rgba(183, 188, 192, 0.75)"
  ]
}